fulladder/fa.vhdl
library ieee;
use ieee.std_logic_1164.all;

entity fa is 
	port(
		a: in std_ulogic;
		b: in std_ulogic;
		cin: in std_ulogic;
		cout: out std_ulogic;
		s: out std_ulogic
	);
end fa;

architecture  behave of fa is
begin
	s <= (a xor b) xor cin;
	cout <= ((a xor b) and cin) or (a and b);
end behave;

fulladder/fa_testbench.vhdl
library ieee;
use ieee.std_logic_1164.all;

entity fa_testbench is
end fa_testbench;

architecture test of fa_testbench is
	component fa
		port(
			a: in std_ulogic;
			b: in std_ulogic;
			cin: in std_ulogic;
			cout: out std_ulogic;
			s: out std_ulogic
		);
	end component;
	
	signal ain, bin, cin, cout, sum : std_logic;

	begin
		full_adder: fa port map (a => ain, b => bin, cin => cin, cout => cout, s => sum);

		process begin

			ain <= '0';
			bin <= '0';
			cin <= '0';
			wait for 1 ns;

			ain <= '0';
			bin <= '0';
			cin <= '1';
			wait for 1 ns;

			ain <= '0';
			bin <= '1';
			cin <= '0';
			wait for 1 ns;

			ain <= '0';
			bin <= '1';
			cin <= '1';
			wait for 1 ns;

			ain <= '1';
			bin <= '0';
			cin <= '0';
			wait for 1 ns;

			ain <= '1';
			bin <= '0';
			cin <= '1';
			wait for 1 ns;

			ain <= '1';
			bin <= '1';
			cin <= '0';
			wait for 1 ns;

			ain <= '1';
			bin <= '1';
			cin <= '1';
			wait for 1 ns;

			assert false report "Reached end of test";
			wait;
		end process;
end test;

fulladder/fa.vcd
$date
  Fri Mar 20 12:51:38 2020
$end
$version
  GHDL v0
$end
$timescale
  1 fs
$end
$scope module standard $end
$upscope $end
$scope module std_logic_1164 $end
$upscope $end
$scope module fa_testbench $end
$var reg 1 ! ain $end
$var reg 1 " bin $end
$var reg 1 # cin $end
$var reg 1 $ cout $end
$var reg 1 % sum $end
$scope module full_adder $end
$var reg 1 & a $end
$var reg 1 ' b $end
$var reg 1 ( cin $end
$var reg 1 ) cout $end
$var reg 1 * s $end
$upscope $end
$upscope $end
$enddefinitions $end
#0
0!
0"
0#
0$
0%
0&
0'
0(
0)
0*
#1000000
1#
1%
1(
1*
#2000000
1"
0#
1'
0(
#3000000
1#
1$
0%
1(
1)
0*
#4000000
1!
0"
0#
0$
1%
1&
0'
0(
0)
1*
#5000000
1#
1$
0%
1(
1)
0*
#6000000
1"
0#
1'
0(
#7000000
1#
1%
1(
1*
